npwPy/__init__.py
npwPy/npwp.py
npwPy-0.0.2.dist-info/LICENSE
npwPy-0.0.2.dist-info/METADATA
npwPy-0.0.2.dist-info/WHEEL
npwPy-0.0.2.dist-info/top_level.txt
npwPy-0.0.2.dist-info/RECORD
