Metadata-Version: 2.1
Name: npwPy
Version: 0.0.2
Summary: this package for checking NPWP number
Home-page: https://github.com/sendaljpt/npwPy
Author: Fajrin Imam Arif
Author-email: fajrinimamarif@gmail.com
License: UNKNOWN
Platform: UNKNOWN
Classifier: Programming Language :: Python :: 3
Classifier: License :: OSI Approved :: MIT License
Classifier: Operating System :: OS Independent
Requires-Python: >=3.6
